elastic_ssh/__init__.py
elastic_ssh/config.py
elastic_ssh/console.py
elastic_ssh/instance.py
elastic_ssh/ssh.py
elastic_ssh-0.1.1.dist-info/LICENSE.md
elastic_ssh-0.1.1.dist-info/METADATA
elastic_ssh-0.1.1.dist-info/WHEEL
elastic_ssh-0.1.1.dist-info/entry_points.txt
elastic_ssh-0.1.1.dist-info/top_level.txt
elastic_ssh-0.1.1.dist-info/RECORD
