Metadata-Version: 2.1
Name: elastic-ssh
Version: 0.1.1
Summary: UNKNOWN
Home-page: UNKNOWN
License: UNKNOWN
Platform: UNKNOWN
Classifier: Programming Language :: Python :: 3
Classifier: License :: OSI Approved :: BSD License
Classifier: Operating System :: OS Independent
Requires-Python: >=3.5
Requires-Dist: questionary (<2.0,>=1.0)
Requires-Dist: boto3 (<2.0,>=1.10.0)
Requires-Dist: click (>=7)
Requires-Dist: click-default-group
Requires-Dist: xdg
